gatewayVoice/__init__.py
gatewayVoice/voiceTesting.py
gatewayVoiceTesting/__init__.py
gatewayVoiceTesting/voiceTesting.py
gatewayVoice-1.0.0.dist-info/LICENSE
gatewayVoice-1.0.0.dist-info/METADATA
gatewayVoice-1.0.0.dist-info/WHEEL
gatewayVoice-1.0.0.dist-info/entry_points.txt
gatewayVoice-1.0.0.dist-info/top_level.txt
gatewayVoice-1.0.0.dist-info/RECORD
