Metadata-Version: 2.1
Name: gatewayVoice
Version: 1.0.0
Summary: Analog Voice Modem Testing
Home-page: UNKNOWN
Author: Abirami
Author-email: abiramig1930@gmail.com
License: MIT
Keywords: analog_modem
Platform: UNKNOWN
Classifier: Programming Language :: Python :: 3
Classifier: License :: OSI Approved :: MIT License
Classifier: Operating System :: OS Independent
License-File: LICENSE
